gimmebio.pji-0.2.1-py3.6-nspkg.pth
gimmebio/pji/__init__.py
gimmebio/pji/cli.py
gimmebio/pji/pji.py
gimmebio/pji/utils.py
gimmebio.pji-0.2.1.dist-info/METADATA
gimmebio.pji-0.2.1.dist-info/RECORD
gimmebio.pji-0.2.1.dist-info/WHEEL
gimmebio.pji-0.2.1.dist-info/namespace_packages.txt
gimmebio.pji-0.2.1.dist-info/top_level.txt
